crawler/__init__.py
crawler/madmonkey_crawler.py
madmonkey/__init__.py
madmonkey/intake.py
tri_star_symbolic_assembly_lang-0.1.167.dist-info/licenses/LICENSE
tsal/__init__.py
tsal/api.py
tsal/agents/__init__.py
tsal/agents/branch_reconciliation.py
tsal/agents/priority_research_team.py
tsal/audit/__init__.py
tsal/audit/brian_self_audit.py
tsal/ci/__init__.py
tsal/ci/symbolic_diff.py
tsal/cli/__init__.py
tsal/cli/beast.py
tsal/cli/brian.py
tsal/cli/brian_optimize.py
tsal/cli/codesummary.py
tsal/cli/meshkeeper.py
tsal/cli/party.py
tsal/cli/reflect.py
tsal/cli/scorer.py
tsal/cli/spiral_api.py
tsal/cli/tsal_sanctum_export.py
tsal/cli/watchdog.py
tsal/core/__init__.py
tsal/core/connectivity.py
tsal/core/constants.py
tsal/core/entangle.py
tsal/core/ethics_engine.py
tsal/core/executor.py
tsal/core/gradient.py
tsal/core/guardian_constants.py
tsal/core/intent_metric.py
tsal/core/jasper_core.py
tsal/core/json_dsl.py
tsal/core/logic_gate.py
tsal/core/madmonkey_handler.py
tsal/core/manifold.py
tsal/core/merge.py
tsal/core/mesh_logger.py
tsal/core/mesh_ops.py
tsal/core/meta_coherence.py
tsal/core/module_registry.py
tsal/core/oaths.py
tsal/core/optimizer_utils.py
tsal/core/opwords.py
tsal/core/phase_math.py
tsal/core/phi_math.py
tsal/core/reflection.py
tsal/core/rev_eng.py
tsal/core/shadow.py
tsal/core/spark_translator.py
tsal/core/spin_algebra.py
tsal/core/spiral_fusion.py
tsal/core/spiral_memory.py
tsal/core/spiral_vector.py
tsal/core/stack_vm.py
tsal/core/state_vector.py
tsal/core/superpos.py
tsal/core/symbols.py
tsal/core/tokenize_flowchart.py
tsal/core/tsal_executor.py
tsal/core/voxel.py
tsal/dashboard/__init__.py
tsal/dashboard/wisdom_bloom.py
tsal/kernels/__init__.py
tsal/kernels/resurrection_node.py
tsal/kernels/temporal_mirror.py
tsal/paradox/__init__.py
tsal/paradox/recursive_compiler.py
tsal/quantum/__init__.py
tsal/quantum/interface.py
tsal/renderer/__init__.py
tsal/renderer/code_render.py
tsal/repair/__init__.py
tsal/repair/self_forking.py
tsal/rl/__init__.py
tsal/rl/madmonkey.py
tsal/schemas/__init__.py
tsal/schemas/python.json
tri_star_symbolic_assembly_lang-0.1.167.dist-info/METADATA
tri_star_symbolic_assembly_lang-0.1.167.dist-info/WHEEL
tri_star_symbolic_assembly_lang-0.1.167.dist-info/entry_points.txt
tri_star_symbolic_assembly_lang-0.1.167.dist-info/top_level.txt
tri_star_symbolic_assembly_lang-0.1.167.dist-info/RECORD
