Metadata-Version: 2.4
Name: tri-star_symbolic_assembly_lang
Version: 0.1.167
Summary: TriStar Assembly Language Core + Brian Spiral Tools
Author: Sam Howells
License: ## LICENCE Options for `Brian`
Requires-Python: >=3.9
License-File: LICENSE
Requires-Dist: requests
Requires-Dist: numpy
Requires-Dist: matplotlib
Requires-Dist: pyyaml
Requires-Dist: esprima
Requires-Dist: fastapi
Requires-Dist: httpx
Provides-Extra: test
Requires-Dist: pytest; extra == "test"
Dynamic: license-file
